[
  {
    "type": "colordef",
    "BLACK": [ 8, 8, 8 ],
    "RED": [ 255, 75, 0 ],
    "GREEN": [ 3, 175, 122 ],
    "BROWN": [ 128, 64, 0 ],
    "BLUE": [ 0, 90, 255 ],
    "MAGENTA": [ 153, 58, 153],
    "CYAN": [ 0, 150, 180 ],
    "GRAY": [ 150, 150, 150 ],
    "DGRAY": [ 99, 99, 99 ],
    "LRED": [ 255, 200, 175 ],
    "LGREEN": [ 0, 255, 0 ],
    "YELLOW": [ 255, 241, 0 ],
    "LBLUE": [ 77, 196, 255 ],
    "LMAGENTA": [ 255, 128, 130 ],
    "LCYAN": [ 0, 240, 255 ],
    "WHITE": [ 255, 255, 255 ]
  }
]
